README.rst
setup.cfg
setup.py
ceph_api/__init__.py
ceph_api/ceph_command.py
ceph_api.egg-info/PKG-INFO
ceph_api.egg-info/SOURCES.txt
ceph_api.egg-info/dependency_links.txt
ceph_api.egg-info/requires.txt
ceph_api.egg-info/top_level.txt
ceph_api/firefly/__init__.py
ceph_api/firefly/ceph_command.py
ceph_api/giant/__init__.py
ceph_api/giant/ceph_command.py
ceph_api/hammer/__init__.py
ceph_api/hammer/ceph_command.py
ceph_api/infernalis/__init__.py
ceph_api/infernalis/ceph_command.py
ceph_api/jewel/__init__.py
ceph_api/jewel/ceph_command.py